<ItemPools>
    <Pool Name="treasure">
        <Item Name="Pliers"/>
        <Item Name="Condensed Milk"/>
        <Item Name="Goat Milk"/>
        <Item Name="Slickwater"/>
        <Item Name="Painkillers" Weight="0.2" DecreaseBy="0.2"/>
        <Item Name="Tech IX"/>
        <Item Name="Pepper X"/>
        <Item Name="Meteor Shower"/>
        <Item Name="Golden Tweezers"/>
        <Item Name="Scattered Tome"/>
        <Item Name="Malicious Brain"/>
        <Item Name="Obsidian Shard"/>
    </Pool>
    <Pool Name="greedTreasure">
        <Item Name="Pliers"/>
        <Item Name="Condensed Milk"/>
        <Item Name="Goat Milk"/>
        <Item Name="Slickwater"/>
        <Item Name="Painkillers" Weight="0.2" DecreaseBy="0.2"/>
        <Item Name="Tech IX"/>
        <Item Name="Pepper X"/>
        <Item Name="Meteor Shower"/>
        <Item Name="Golden Tweezers"/>
        <Item Name="Scattered Tome"/>
        <Item Name="Malicious Brain"/>
    </Pool>

    <Pool Name="boss">
        <Item Name="Caramel Apple"/>
        <Item Name="Eyestrain"/>
    </Pool>
    <Pool Name="greedBoss">
        <Item Name="Caramel Apple"/>
        <Item Name="Eyestrain"/>
    </Pool>

    <Pool Name="shop">
        
    </Pool>
    <Pool Name="greedShop">
        
    </Pool>

    <Pool Name="devil">
        <Item Name="Blood Ritual"/>
        <Item Name="Sigil of Greed"/>
    </Pool>
    <Pool Name="greedDevil">
        <Item Name="Blood Ritual"/>
        <Item Name="Sigil of Greed" Weight="0.5" DecreaseBy="0.5"/>
    </Pool>

    <Pool Name="angel">
        <Item Name="Silk Bag"/>
        <Item Name="Blessed Ring"/>
    </Pool>
    <Pool Name="greedAngel">
        <Item Name="Silk Bag"/>
        <Item Name="Blessed Ring"/>
    </Pool>

    <Pool Name="curse">
        <Item Name="Pliers"/>
        <Item Name="Lion Skull"/>
        <Item Name="Painkillers"/>
    </Pool>
    <Pool Name="greedCurse">
        <Item Name="Pliers"/>
        <Item Name="Painkillers"/>
    </Pool>

    <Pool Name="redChest">
        <Item Name="Obsidian Shard"/>
        <Item Name="Painkillers" Weight="0.75" DecreaseBy="0.75"/>
    </Pool>

    <Pool Name="secret">
        <Item Name="4 4"/>
        <Item Name="Fatal Signal"/>
    </Pool>
    <Pool Name="greedSecret">
        <Item Name="4 4"/>
        <Item Name="Fatal Signal"/>
    </Pool>

    <Pool Name="demonBeggar">
        <Item Name="Pliers"/>
    </Pool>
</ItemPools>